{
  "topic": "DSA: Bit Manipulation",
  "description": "Bitwise operators, masks, and binary trickery",
  "icon": "🔢",
  "accent": "#14b8a6",
  "source": "bitmanipulation.md",
  "questions": [
    {
      "id": 1,
      "question": "Check if a Number is a Power of Two",
      "leetcode_link": "https://leetcode.com/problems/check-if-a-number-is-a-power-of-two/",
      "level": "Easy",
      "priority": "P1",
      "problem": "Given an integer `n`, return `true` if it is a power of two, otherwise return `false`.\n\n```\nInput:  n = 16  → Output: true   (2^4)\nInput:  n = 18  → Output: false\nInput:  n = 1   → Output: true   (2^0)\nInput:  n = 0   → Output: false\n```",
      "intuition": "A power of two in binary has **exactly one bit set**:\n```\n1  → 0001\n2  → 0010\n4  → 0100\n8  → 1000\n```\nThe trick `n & (n - 1)` removes the lowest set bit. If the result is 0, there was only one bit — a power of two.\n\n```\nn     = 1000  (8)\nn - 1 = 0111  (7)\nn & (n-1) = 0000 → Power of two ✓\n\nn     = 1010  (10)\nn - 1 = 1001  (9)\nn & (n-1) = 1000 → NOT zero → Not a power of two ✗\n```\n\n**Why This Approach**\n- **O(1)** time and space — just a single bitwise AND.\n- No loops, no log math. This is the canonical interview answer.",
      "code": "```java\npublic class PowerOfTwo {\n\n    public boolean isPowerOfTwo(int n) {\n        // n must be positive AND removing its lowest set bit gives 0\n        return n > 0 && (n & (n - 1)) == 0;\n    }\n\n    // ---- Test Cases ----\n    public static void main(String[] args) {\n        PowerOfTwo sol = new PowerOfTwo();\n\n        System.out.println(sol.isPowerOfTwo(1));   // true\n        System.out.println(sol.isPowerOfTwo(2));   // true\n        System.out.println(sol.isPowerOfTwo(16));  // true\n        System.out.println(sol.isPowerOfTwo(18));  // false\n        System.out.println(sol.isPowerOfTwo(0));   // false\n        System.out.println(sol.isPowerOfTwo(-4));  // false\n    }\n}\n```",
      "test_cases": "| Input | Expected | Reason |\n|---|---|---|\n| 1 | true | 2^0 |\n| 2 | true | 2^1 |\n| 16 | true | 2^4 |\n| 18 | false | 10 + 8 |\n| 0 | false | Edge case |\n| -4 | false | Negative |",
      "images": []
    },
    {
      "id": 2,
      "question": "Count Set Bits (Hamming Weight / Popcount)",
      "leetcode_link": "https://leetcode.com/problems/count-set-bits/",
      "level": "Easy",
      "priority": "P1",
      "problem": "Given a positive integer `n`, return the number of `1` bits in its binary representation (also called Hamming weight or popcount).\n\n```\nInput: n = 11 (binary: 1011) → Output: 3\nInput: n = 128 (binary: 10000000) → Output: 1\n```",
      "intuition": "**Brian Kernighan's Algorithm**: `n & (n - 1)` always clears the rightmost set bit. Count how many times you can do this before `n` becomes 0 — that's the number of set bits.\n\n```\nn = 1011 (11)\nStep 1: n & (n-1) = 1011 & 1010 = 1010  count=1\nStep 2: n & (n-1) = 1010 & 1001 = 1000  count=2\nStep 3: n & (n-1) = 1000 & 0111 = 0000  count=3\nn = 0 → stop\n```\n\n**Why This Approach**\n- Iterates only as many times as there are **set bits**, not all 32 bits.\n- Best when the number is sparse (few set bits).\n- Contrast: naive approach shifts all 32 bits regardless.",
      "code": "```java\npublic class CountSetBits {\n\n    // Brian Kernighan's Algorithm — O(number of set bits)\n    public int hammingWeight(int n) {\n        int count = 0;\n        while (n != 0) {\n            n = n & (n - 1); // clear the lowest set bit\n            count++;\n        }\n        return count;\n    }\n\n    // Alternative: DP / lookup approach using Integer.bitCount (built-in)\n    public int hammingWeightBuiltIn(int n) {\n        return Integer.bitCount(n);\n    }\n\n    // ---- Test Cases ----\n    public static void main(String[] args) {\n        CountSetBits sol = new CountSetBits();\n\n        System.out.println(sol.hammingWeight(11));          // 3  (1011)\n        System.out.println(sol.hammingWeight(128));         // 1  (10000000)\n        System.out.println(sol.hammingWeight(0));           // 0\n        System.out.println(sol.hammingWeight(0xFFFFFFFF));  // 32 (all bits set)\n        System.out.println(sol.hammingWeight(7));           // 3  (111)\n    }\n}\n```",
      "test_cases": "| Input | Binary | Expected |\n|---|---|---|\n| 11 | 1011 | 3 |\n| 128 | 10000000 | 1 |\n| 0 | 00...0 | 0 |\n| 7 | 111 | 3 |\n| 0xFFFFFFFF | all 1s | 32 |",
      "images": []
    },
    {
      "id": 3,
      "question": "Find the Single Number (XOR Trick)",
      "leetcode_link": "https://leetcode.com/problems/find-the-single-number/",
      "level": "Easy",
      "priority": "P1",
      "problem": "Given a non-empty array where every element appears **twice** except one — find that one element. Must run in O(n) time and O(1) space.\n\n```\nInput: [4, 1, 2, 1, 2]  → Output: 4\nInput: [2, 2, 1]         → Output: 1\n```",
      "intuition": "XOR has two beautiful properties:\n- `a ^ a = 0` (same numbers cancel)\n- `a ^ 0 = a` (XOR with 0 is identity)\n\nXOR everything together — all duplicates cancel out, leaving just the unique number.\n\n```\n4 ^ 1 ^ 2 ^ 1 ^ 2\n= 4 ^ (1 ^ 1) ^ (2 ^ 2)\n= 4 ^ 0 ^ 0\n= 4\n```\n\n**Why This Approach**\n- This is the **most elegant** bit manipulation trick. O(n) time, O(1) space.\n- No hash map, no sorting needed.\n- Interviewers love asking why XOR works — explain the two properties above.",
      "code": "```java\npublic class SingleNumber {\n\n    public int singleNumber(int[] nums) {\n        int result = 0;\n        for (int num : nums) {\n            result ^= num; // XOR cancels duplicates\n        }\n        return result;\n    }\n\n    // ---- Test Cases ----\n    public static void main(String[] args) {\n        SingleNumber sol = new SingleNumber();\n\n        System.out.println(sol.singleNumber(new int[]{4, 1, 2, 1, 2}));  // 4\n        System.out.println(sol.singleNumber(new int[]{2, 2, 1}));         // 1\n        System.out.println(sol.singleNumber(new int[]{1}));               // 1\n        System.out.println(sol.singleNumber(new int[]{0, 1, 0}));         // 1\n    }\n}\n```",
      "test_cases": "| Input | Expected |\n|---|---|\n| [4, 1, 2, 1, 2] | 4 |\n| [2, 2, 1] | 1 |\n| [1] | 1 |\n| [0, 1, 0] | 1 |",
      "images": []
    },
    {
      "id": 4,
      "question": "Find Two Non-Repeating Numbers",
      "leetcode_link": "https://leetcode.com/problems/find-two-non-repeating-numbers/",
      "level": "Medium",
      "priority": "P1",
      "problem": "Given an array where every element appears exactly **twice** except **two** elements — find those two elements. O(n) time, O(1) space.\n\n```\nInput: [1, 2, 3, 2, 1, 4]  → Output: [3, 4]\n```",
      "intuition": "**Step 1**: XOR all elements → result is `a ^ b` (the two unique numbers).\n**Step 2**: Find any set bit in `a ^ b` (use rightmost: `xor & (-xor)`). This bit differs between `a` and `b`.\n**Step 3**: Split all numbers into two groups based on that bit. XOR each group separately → one group gives `a`, other gives `b`.\n\n```\nArray: [1, 2, 3, 2, 1, 4]\nXOR all: 1^2^3^2^1^4 = 3^4 = 011 ^ 100 = 111 (7)\n\nRightmost set bit of 7 = 001 (bit 0)\n\nGroup A (bit 0 is 1): 1, 3, 1  → XOR = 3\nGroup B (bit 0 is 0): 2, 2, 4  → XOR = 4\n\nAnswer: 3, 4 ✓\n```\n\n**Why This Approach**\nExtends the XOR trick from problem 3. The key insight is using a **differentiating bit** to separate the two uniques into different groups.",
      "code": "```java\npublic class TwoSingleNumbers {\n\n    public int[] singleNumber(int[] nums) {\n        // Step 1: XOR all to get a ^ b\n        int xor = 0;\n        for (int num : nums) xor ^= num;\n\n        // Step 2: Find rightmost set bit (differs between a and b)\n        int diffBit = xor & (-xor);\n\n        // Step 3: Partition and XOR separately\n        int a = 0, b = 0;\n        for (int num : nums) {\n            if ((num & diffBit) != 0) a ^= num;\n            else                      b ^= num;\n        }\n        return new int[]{a, b};\n    }\n\n    // ---- Test Cases ----\n    public static void main(String[] args) {\n        TwoSingleNumbers sol = new TwoSingleNumbers();\n\n        int[] res1 = sol.singleNumber(new int[]{1, 2, 3, 2, 1, 4});\n        System.out.println(res1[0] + \", \" + res1[1]); // 3, 4\n\n        int[] res2 = sol.singleNumber(new int[]{5, 7, 5, 9});\n        System.out.println(res2[0] + \", \" + res2[1]); // 7, 9\n    }\n}\n```",
      "test_cases": "| Input | Expected |\n|---|---|\n| [1, 2, 3, 2, 1, 4] | [3, 4] |\n| [5, 7, 5, 9] | [7, 9] |\n| [1, 1, 2, 3] | [2, 3] |",
      "images": []
    },
    {
      "id": 5,
      "question": "Reverse Bits of an Integer",
      "leetcode_link": "https://leetcode.com/problems/reverse-bits-of-an-integer/",
      "level": "Easy",
      "priority": "P1",
      "problem": "Reverse all 32 bits of an unsigned integer.\n\n```\nInput:  43261596  (00000010100101000001111010011100)\nOutput: 964176192 (00111001011110000010100101000000)\n```",
      "intuition": "Process the input bit by bit from LSB to MSB, building the result from MSB to LSB:\n- Extract the last bit of `n` using `n & 1`\n- Shift result left and OR the extracted bit in\n- Shift `n` right by 1\n\nDo this 32 times.\n\n```\nn    = ...1011\nPass 1: result = (0 << 1) | 1 = 1,  n = ...101\nPass 2: result = (1 << 1) | 1 = 3,  n = ...10\nPass 3: result = (3 << 1) | 0 = 6,  n = ...1\nPass 4: result = (6 << 1) | 1 = 13, n = 0\n```\n\n**Why This Approach**\nStraightforward O(32) = O(1). For repeated calls (follow-up), cache 8-bit chunks in a lookup table for O(1) per call.",
      "code": "```java\npublic class ReverseBits {\n\n    public int reverseBits(int n) {\n        int result = 0;\n        for (int i = 0; i < 32; i++) {\n            result = (result << 1) | (n & 1); // pull LSB of n into result\n            n >>= 1;\n        }\n        return result;\n    }\n\n    // ---- Test Cases ----\n    public static void main(String[] args) {\n        ReverseBits sol = new ReverseBits();\n\n        // 43261596 → 964176192\n        System.out.println(sol.reverseBits(43261596));\n\n        // 0 → 0\n        System.out.println(sol.reverseBits(0));\n\n        // -1 (all 1s) → -1 (all 1s reversed = all 1s)\n        System.out.println(sol.reverseBits(-1));\n\n        // 1 (00...001) → -2147483648 (10...000)\n        System.out.println(sol.reverseBits(1));\n    }\n}\n```",
      "test_cases": "| Input (decimal) | Expected Output |\n|---|---|\n| 43261596 | 964176192 |\n| 0 | 0 |\n| -1 (all 32 bits set) | -1 |\n| 1 | -2147483648 |",
      "images": []
    },
    {
      "id": 6,
      "question": "Find the Missing Number",
      "leetcode_link": "https://leetcode.com/problems/find-the-missing-number/",
      "level": "Easy",
      "priority": "P1",
      "problem": "Given an array containing `n` distinct numbers in the range `[0, n]`, return the one number that is missing.\n\n```\nInput: [3, 0, 1]  → Output: 2\nInput: [0, 1]     → Output: 2\nInput: [9,6,4,2,3,5,7,0,1] → Output: 8\n```",
      "intuition": "**XOR approach**: XOR all indices `0..n` with all array values. Pairs cancel, leaving the missing number.\n\n```\nArray = [3, 0, 1], n = 3\nXOR indices: 0 ^ 1 ^ 2 ^ 3 = 0\nXOR values:  3 ^ 0 ^ 1\nTotal XOR:   0^1^2^3 ^ 3^0^1\n           = (0^0)^(1^1)^2^(3^3) = 2 ✓\n```\n\n**Why This Approach**\nBoth sum formula (n*(n+1)/2 - sum) and XOR work. XOR avoids integer overflow risk for very large `n`.",
      "code": "```java\npublic class MissingNumber {\n\n    // XOR approach — O(n) time, O(1) space\n    public int missingNumber(int[] nums) {\n        int xor = nums.length; // start with n\n        for (int i = 0; i < nums.length; i++) {\n            xor ^= i ^ nums[i]; // XOR index and value\n        }\n        return xor;\n    }\n\n    // Alternative: sum formula\n    public int missingNumberSum(int[] nums) {\n        int n = nums.length;\n        int expectedSum = n * (n + 1) / 2;\n        int actualSum = 0;\n        for (int num : nums) actualSum += num;\n        return expectedSum - actualSum;\n    }\n\n    // ---- Test Cases ----\n    public static void main(String[] args) {\n        MissingNumber sol = new MissingNumber();\n\n        System.out.println(sol.missingNumber(new int[]{3, 0, 1}));            // 2\n        System.out.println(sol.missingNumber(new int[]{0, 1}));               // 2\n        System.out.println(sol.missingNumber(new int[]{9,6,4,2,3,5,7,0,1})); // 8\n        System.out.println(sol.missingNumber(new int[]{0}));                  // 1\n    }\n}\n```",
      "test_cases": "| Input | Expected |\n|---|---|\n| [3, 0, 1] | 2 |\n| [0, 1] | 2 |\n| [9,6,4,2,3,5,7,0,1] | 8 |\n| [0] | 1 |",
      "images": []
    },
    {
      "id": 7,
      "question": "Subsets Generation using Bitmask",
      "leetcode_link": "https://leetcode.com/problems/subsets-generation-using-bitmask/",
      "level": "Medium",
      "priority": "P1",
      "problem": "Given an array of **distinct** integers, return all possible subsets (the power set). Order doesn't matter.\n\n```\nInput: [1, 2, 3]\nOutput: [[], [1], [2], [1,2], [3], [1,3], [2,3], [1,2,3]]\n```",
      "intuition": "For `n` elements there are `2^n` subsets. Each integer from `0` to `2^n - 1` is a **bitmask** where bit `i` being set means element `i` is included.\n\n```\nn = 3, masks 0..7:\n000 → {}\n001 → {1}\n010 → {2}\n011 → {1,2}\n100 → {3}\n101 → {1,3}\n110 → {2,3}\n111 → {1,2,3}\n```\n\n**Why This Approach**\n- No recursion needed. Bit `i` of mask directly encodes \"include element i\".\n- Generalizes elegantly to set problems, combinatorics, DP on subsets.\n- Foundation for bitmask DP (TSP, covered sets, etc.)",
      "code": "```java\nimport java.util.*;\n\npublic class Subsets {\n\n    public List<List<Integer>> subsets(int[] nums) {\n        int n = nums.length;\n        int total = 1 << n; // 2^n\n        List<List<Integer>> result = new ArrayList<>();\n\n        for (int mask = 0; mask < total; mask++) {\n            List<Integer> subset = new ArrayList<>();\n            for (int i = 0; i < n; i++) {\n                if ((mask & (1 << i)) != 0) { // bit i is set?\n                    subset.add(nums[i]);\n                }\n            }\n            result.add(subset);\n        }\n        return result;\n    }\n\n    // ---- Test Cases ----\n    public static void main(String[] args) {\n        Subsets sol = new Subsets();\n\n        List<List<Integer>> res = sol.subsets(new int[]{1, 2, 3});\n        System.out.println(\"Total subsets: \" + res.size()); // 8\n        res.forEach(System.out::println);\n\n        // Edge: single element\n        System.out.println(sol.subsets(new int[]{0})); // [[], [0]]\n    }\n}\n```",
      "test_cases": "| Input | # Subsets | Sample Subsets |\n|---|---|---|\n| [1, 2, 3] | 8 | [], [1], [2], [1,2], ... |\n| [0] | 2 | [], [0] |\n| [] | 1 | [] |\n| [1,2,3,4] | 16 | all 16 combinations |",
      "images": []
    },
    {
      "id": 8,
      "question": "Maximum XOR of Two Numbers in an Array",
      "leetcode_link": "https://leetcode.com/problems/maximum-xor-of-two-numbers-in-an-array/",
      "level": "Medium",
      "priority": "P1",
      "problem": "Given an integer array `nums`, return the maximum result of `nums[i] XOR nums[j]`, where `0 <= i <= j < n`.\n\n```\nInput: [3, 10, 5, 25, 2, 8]  → Output: 28  (5 XOR 25 = 11101 = 28? No: 5=00101, 25=11001, XOR=11100=28) ✓\nInput: [14, 70, 53, 83, 49, 91, 36, 80, 92, 51] → Output: 127\n```",
      "intuition": "**Greedy bit-by-bit from MSB**: For maximum XOR, we want as many high bits set as possible. At each bit position (from 31 down to 0), we greedily try to set it in the answer:\n1. Collect all prefixes (using the current bit length) into a set.\n2. Tentatively assume the current bit can be 1 → `candidate = current_ans | (1 << bit)`.\n3. Check if any two prefixes `a` and `b` exist in the set such that `a ^ b == candidate`.\n4. This works because `a ^ b = candidate` ⟺ `a ^ candidate = b` — check if `b` is in the set.\n\n**Why This Approach**\n- O(32n) = O(n) per bit level. Total O(32n) = O(n).\n- Greedy works because each bit decision is independent — fixing a higher bit never prevents a lower bit from being 1.\n- Can also be solved with a binary Trie: insert all numbers, then for each number greedily traverse opposite bits.",
      "code": "```java\nimport java.util.*;\n\npublic class MaximumXOR {\n\n    // Greedy + HashSet approach — O(32n) = O(n)\n    public int findMaximumXOR(int[] nums) {\n        int maxXor = 0;\n        int mask = 0;\n\n        for (int i = 31; i >= 0; i--) {\n            mask |= (1 << i); // include bit i in prefix\n\n            // Collect all prefixes with current mask\n            Set<Integer> prefixes = new HashSet<>();\n            for (int num : nums) {\n                prefixes.add(num & mask);\n            }\n\n            // Tentatively set this bit in the answer\n            int candidate = maxXor | (1 << i);\n\n            // Check if two prefixes XOR to candidate\n            for (int prefix : prefixes) {\n                if (prefixes.contains(candidate ^ prefix)) {\n                    maxXor = candidate;\n                    break;\n                }\n            }\n        }\n        return maxXor;\n    }\n\n    // ---- Test Cases ----\n    public static void main(String[] args) {\n        MaximumXOR sol = new MaximumXOR();\n\n        System.out.println(sol.findMaximumXOR(new int[]{3, 10, 5, 25, 2, 8}));       // 28\n        System.out.println(sol.findMaximumXOR(new int[]{0}));                          // 0\n        System.out.println(sol.findMaximumXOR(new int[]{2, 4}));                       // 6\n        System.out.println(sol.findMaximumXOR(\n            new int[]{14,70,53,83,49,91,36,80,92,51}));                                // 127\n    }\n}\n```",
      "test_cases": "| Input | Expected |\n|---|---|\n| [3, 10, 5, 25, 2, 8] | 28 |\n| [0] | 0 |\n| [2, 4] | 6 |\n| [14,70,53,83,49,91,36,80,92,51] | 127 |",
      "images": []
    },
    {
      "id": 9,
      "question": "Counting Bits — Number of 1s for 0 to N",
      "leetcode_link": "https://leetcode.com/problems/counting-bits-number-of-1s-for-0-to-n/",
      "level": "Easy",
      "priority": "P1",
      "problem": "Given an integer `n`, return an array `ans` of length `n + 1` such that for each `i` (0 ≤ i ≤ n), `ans[i]` is the **number of 1's** in the binary representation of `i`.\n\n```\nInput: n = 5\nOutput: [0, 1, 1, 2, 1, 2]\n(0→0, 1→1, 2→1, 3→2, 4→1, 5→2)\n```",
      "intuition": "**DP + bit trick**: For any number `i`:\n- If `i` is even: `bits[i] = bits[i >> 1]` (right shift just removes a trailing 0, bit count same)\n- If `i` is odd:  `bits[i] = bits[i >> 1] + 1` (right shift removes the trailing 1)\n\nCombined: `bits[i] = bits[i >> 1] + (i & 1)`\n\n```\ni=0: 0\ni=1: bits[0] + 1 = 1\ni=2: bits[1] + 0 = 1\ni=3: bits[1] + 1 = 2\ni=4: bits[2] + 0 = 1\ni=5: bits[2] + 1 = 2\n```\n\n**Why This Approach**\n- O(n) time, O(n) space (output).\n- Builds on previously computed values — classic DP pattern.\n- Avoids calling `hammingWeight` repeatedly (which would be O(n log n)).",
      "code": "```java\npublic class CountingBits {\n\n    public int[] countBits(int n) {\n        int[] bits = new int[n + 1];\n        for (int i = 1; i <= n; i++) {\n            // Right-shift reuses smaller subproblem; (i & 1) adds the LSB\n            bits[i] = bits[i >> 1] + (i & 1);\n        }\n        return bits;\n    }\n\n    // ---- Test Cases ----\n    public static void main(String[] args) {\n        CountingBits sol = new CountingBits();\n\n        printArray(sol.countBits(0));  // [0]\n        printArray(sol.countBits(1));  // [0, 1]\n        printArray(sol.countBits(5));  // [0, 1, 1, 2, 1, 2]\n        printArray(sol.countBits(8));  // [0,1,1,2,1,2,2,3,1]\n    }\n\n    static void printArray(int[] arr) {\n        StringBuilder sb = new StringBuilder(\"[\");\n        for (int i = 0; i < arr.length; i++) {\n            sb.append(arr[i]);\n            if (i < arr.length - 1) sb.append(\", \");\n        }\n        System.out.println(sb.append(\"]\"));\n    }\n}\n```",
      "test_cases": "| n | Expected Output |\n|---|---|\n| 0 | [0] |\n| 1 | [0, 1] |\n| 5 | [0, 1, 1, 2, 1, 2] |\n| 8 | [0,1,1,2,1,2,2,3,1] |",
      "images": []
    },
    {
      "id": 10,
      "question": "Single Number III — Element Appearing Once When Others Appear Three Times",
      "leetcode_link": "https://leetcode.com/problems/single-number-iii-element-appearing-once-when-others-appear-three-times/",
      "level": "Medium",
      "priority": "P1",
      "problem": "Given an integer array where every element appears **three times** except for **one** element which appears exactly once. Find that element. O(n) time, O(1) space.\n\n```\nInput: [2, 2, 3, 2]    → Output: 3\nInput: [0, 1, 0, 1, 0, 1, 99] → Output: 99\n```",
      "intuition": "For each bit position, count the total number of 1s across all numbers. If the unique number has a 1 in that bit, the count will **not** be divisible by 3.\n\n**Bit counting approach**: For each of the 32 bits, sum how many numbers have that bit set. `count % 3` gives the unique number's bit at that position.\n\n**State machine approach (advanced O(1) space, no loop per bit)**\nUse two variables `ones` and `twos` to track bits seen once and twice. When a bit is seen three times it resets to 0.\n\n```\nones = bits seen 1 time (mod 3)\ntwos = bits seen 2 times (mod 3)\n\nFor each number x:\n  ones = (ones ^ x) & ~twos\n  twos = (twos ^ x) & ~ones\n```\n\n**Why This Approach**\nThe bit-count approach is easy to reason about. The state machine is the interview gold standard — it handles the \"three times\" constraint with pure bit operations, no extra array.",
      "code": "```java\npublic class SingleNumberIII {\n\n    // Approach 1: Bit counting — O(32n) = O(n)\n    public int singleNumberBitCount(int[] nums) {\n        int result = 0;\n        for (int i = 0; i < 32; i++) {\n            int sum = 0;\n            for (int num : nums) {\n                sum += (num >> i) & 1; // count 1s at bit i\n            }\n            if (sum % 3 != 0) {\n                result |= (1 << i); // this bit belongs to the unique number\n            }\n        }\n        return result;\n    }\n\n    // Approach 2: State machine — O(n) time, O(1) space (elegant)\n    public int singleNumber(int[] nums) {\n        int ones = 0, twos = 0;\n        for (int num : nums) {\n            ones = (ones ^ num) & ~twos;  // add to ones if not in twos\n            twos = (twos ^ num) & ~ones;  // add to twos if not in ones\n        }\n        return ones; // ones holds bits seen exactly once\n    }\n\n    // ---- Test Cases ----\n    public static void main(String[] args) {\n        SingleNumberIII sol = new SingleNumberIII();\n\n        System.out.println(sol.singleNumber(new int[]{2, 2, 3, 2}));           // 3\n        System.out.println(sol.singleNumber(new int[]{0,1,0,1,0,1,99}));       // 99\n        System.out.println(sol.singleNumber(new int[]{-2,-2,1,1,-3,1,-3,-3,-4,-2})); // -4\n        System.out.println(sol.singleNumber(new int[]{1, 1, 1, 3}));           // 3\n    }\n}\n```",
      "test_cases": "| Input | Expected |\n|---|---|\n| [2, 2, 3, 2] | 3 |\n| [0,1,0,1,0,1,99] | 99 |\n| [-2,-2,1,1,-3,1,-3,-3,-4,-2] | -4 |\n| [1, 1, 1, 3] | 3 |",
      "images": []
    }
  ]
}